LICENSE
README.rst
pyproject.toml
openet/__init__.py
openet/ptjpl/__init__.py
openet/ptjpl/collection.py
openet/ptjpl/daily_integration.py
openet/ptjpl/daylight_hours.py
openet/ptjpl/image.py
openet/ptjpl/interpolate.py
openet/ptjpl/landsat.py
openet/ptjpl/meteorology.py
openet/ptjpl/ptjpl.py
openet/ptjpl/solar_azimuth.py
openet/ptjpl/solar_zenith_angle.py
openet/ptjpl/utils.py
openet/ptjpl/vegetation.py
openet/ptjpl/old/et.py
openet/ptjpl/tests/conftest.py
openet/ptjpl/tests/test_a_utils.py
openet/ptjpl/tests/test_b_daily_integration.py
openet/ptjpl/tests/test_b_daylight_hours.py
openet/ptjpl/tests/test_b_landsat.py
openet/ptjpl/tests/test_b_meteorology.py
openet/ptjpl/tests/test_b_solar_azimuth.py
openet/ptjpl/tests/test_b_solar_zenith_angle.py
openet/ptjpl/tests/test_b_vegetation.py
openet/ptjpl/tests/test_c_ptjpl.py
openet/ptjpl/tests/test_d_image.py
openet/ptjpl/tests/test_e_collection.py
openet/ptjpl/tests/test_e_interpolate.py
openet_ptjpl.egg-info/PKG-INFO
openet_ptjpl.egg-info/SOURCES.txt
openet_ptjpl.egg-info/dependency_links.txt
openet_ptjpl.egg-info/requires.txt
openet_ptjpl.egg-info/top_level.txt