Metadata-Version: 2.1
Name: openet-ptjpl
Version: 0.4.1
Summary: Earth Engine implementation of the PTJPL model
Author-email: Gregory Halverson <Gregory.H.Halverson@jpl.nasa.gov>, Josh Fisher <joshbfisher@gmail.com>
Maintainer-email: Gregory Halverson <Gregory.H.Halverson@jpl.nasa.gov>
License:                                  Apache License
Project-URL: Homepage, https://github.com/Open-ET/openet-ptjpl
Keywords: PTJPL,OpenET,Earth Engine,Evapotranspiration,Landsat
Classifier: Programming Language :: Python :: 3
Classifier: License :: OSI Approved :: Apache Software License
Classifier: Operating System :: OS Independent
Requires-Python: >=3.8
License-File: LICENSE
Requires-Dist: earthengine-api>=0.1.392
Requires-Dist: openet-core>=0.6.0
Requires-Dist: python-dateutil
Provides-Extra: test
Requires-Dist: pytest; extra == "test"
